grebakker.py
grebakker-0.4.2.dist-info/licenses/LICENSE
grebakker-0.4.2.dist-info/METADATA
grebakker-0.4.2.dist-info/WHEEL
grebakker-0.4.2.dist-info/entry_points.txt
grebakker-0.4.2.dist-info/top_level.txt
grebakker-0.4.2.dist-info/RECORD
