Metadata-Version: 2.4
Name: grebakker
Version: 0.4.2
Summary: greyrat's backupper for hackers
Home-page: http://grebakker.readthedocs.org/
Download-URL: http://pypi.python.org/pypi/grebakker
Author: dkrajzew
Author-email: d.krajzewicz@gmail.com
License: GPL
Project-URL: Documentation, https://grebakker.readthedocs.io/
Project-URL: Source, https://github.com/dkrajzew/grebakker
Project-URL: Tracker, https://github.com/dkrajzew/grebakker/issues
Project-URL: Discussions, https://github.com/dkrajzew/grebakker/discussions
Classifier: Development Status :: 4 - Beta
Classifier: Environment :: Console
Classifier: Programming Language :: Python
Classifier: Programming Language :: Python :: 3
Classifier: Operating System :: OS Independent
Classifier: Intended Audience :: Developers
Classifier: Intended Audience :: Information Technology
Classifier: Intended Audience :: Other Audience
Requires-Python: >=3, <4
License-File: LICENSE
Dynamic: author
Dynamic: author-email
Dynamic: classifier
Dynamic: description
Dynamic: description-content-type
Dynamic: download-url
Dynamic: home-page
Dynamic: license
Dynamic: license-file
Dynamic: project-url
Dynamic: requires-python
Dynamic: summary
